Metadata-Version: 2.4
Name: django-structurator
Version: 1.2.1
Summary: A lightweight CLI tool that helps you create Django projects and apps with a clean, scalable architecture—without boilerplate or repetitive setup.
Author: @maulik-0207
License: MIT
Project-URL: Documentation, https://github.com/maulik-0207/django-structurator/blob/master/docs/README.md
Project-URL: Source, https://github.com/maulik-0207/django-structurator
Keywords: django,project-generator,cli,tool,django-cli
Classifier: Programming Language :: Python :: 3
Classifier: Programming Language :: Python :: 3.8
Classifier: Programming Language :: Python :: 3 :: Only
Classifier: License :: OSI Approved :: MIT License
Classifier: Operating System :: OS Independent
Classifier: Framework :: Django
Requires-Python: >=3.8
License-File: LICENSE
Requires-Dist: django>=3.2
Dynamic: license-file
